lexcube/__init__.py
lexcube/_frontend.py
lexcube/_version.py
lexcube/cube3d.py
lexcube/labextension/package.json
lexcube/labextension/static/122.05a9fbb1979b7f2e4231.js
lexcube/labextension/static/269.530ee171bbbf5194c890.js
lexcube/labextension/static/509.81e0d9f5b1cd700c7a7c.js
lexcube/labextension/static/54.63ff02f5f1a5f3323f04.js
lexcube/labextension/static/54.63ff02f5f1a5f3323f04.js.LICENSE.txt
lexcube/labextension/static/964.ecb8dcf502d89a442482.js
lexcube/labextension/static/remoteEntry.47fb11dc02aad3235473.js
lexcube/labextension/static/style.js
lexcube/labextension/static/third-party-licenses.json
lexcube/lexcube_server/.dockerignore
lexcube/lexcube_server/.gitignore
lexcube/lexcube_server/Dockerfile
lexcube/lexcube_server/config_example.json
lexcube/lexcube_server/requirements-core.txt
lexcube/lexcube_server/.vscode/launch.json
lexcube/lexcube_server/src/lexcube_widget.py
lexcube/lexcube_server/src/tile_server.py
lexcube/nbextension/extension.js
lexcube/nbextension/index.js
lexcube/nbextension/index.js.map
lexcube/tests/__init__.py
lexcube/tests/conftest.py
lexcube/tests/test_example.py
lexcube/tests/test_nbextension_path.py
lexcube-1.0.3.data/data/share/jupyter/labextensions/lexcube/package.json
lexcube-1.0.3.data/data/share/jupyter/labextensions/lexcube/static/122.05a9fbb1979b7f2e4231.js
lexcube-1.0.3.data/data/share/jupyter/labextensions/lexcube/static/269.530ee171bbbf5194c890.js
lexcube-1.0.3.data/data/share/jupyter/labextensions/lexcube/static/509.81e0d9f5b1cd700c7a7c.js
lexcube-1.0.3.data/data/share/jupyter/labextensions/lexcube/static/54.63ff02f5f1a5f3323f04.js
lexcube-1.0.3.data/data/share/jupyter/labextensions/lexcube/static/54.63ff02f5f1a5f3323f04.js.LICENSE.txt
lexcube-1.0.3.data/data/share/jupyter/labextensions/lexcube/static/964.ecb8dcf502d89a442482.js
lexcube-1.0.3.data/data/share/jupyter/labextensions/lexcube/static/remoteEntry.47fb11dc02aad3235473.js
lexcube-1.0.3.data/data/share/jupyter/labextensions/lexcube/static/style.js
lexcube-1.0.3.dist-info/METADATA
lexcube-1.0.3.dist-info/WHEEL
lexcube-1.0.3.dist-info/licenses/COPYING
lexcube-1.0.3.dist-info/RECORD
