Metadata-Version: 2.4
Name: lexcube
Version: 1.0.3
Summary: Lexcube: 3D Data Cube Visualization in Jupyter Notebooks
Project-URL: Homepage, https://github.com/msoechting/lexcube
Author-email: Maximilian Söchting <maximilian.soechting@uni-leipzig.de>
License:                     GNU GENERAL PUBLIC LICENSE
License-File: COPYING
Keywords: IPython,Jupyter,Widgets
Classifier: Development Status :: 4 - Beta
Classifier: Framework :: Jupyter
Classifier: Intended Audience :: Developers
Classifier: Intended Audience :: Science/Research
Classifier: License :: OSI Approved :: GNU General Public License v3 or later (GPLv3+)
Classifier: Programming Language :: JavaScript
Classifier: Programming Language :: Python
Classifier: Programming Language :: Python :: 3
Classifier: Programming Language :: Python :: 3.9
Classifier: Programming Language :: Python :: 3.10
Classifier: Programming Language :: Python :: 3.11
Classifier: Programming Language :: Python :: 3.12
Requires-Python: >=3.9
Requires-Dist: aiohttp>=3.7.4
Requires-Dist: bottleneck>=1.3.7
Requires-Dist: cachey>=0.2.1
Requires-Dist: dask>=2022.12.0
Requires-Dist: ipywidgets==7.8.3
Requires-Dist: netcdf4>=1.6.3
Requires-Dist: opencv-python-headless>=4.7.0.72
Requires-Dist: xarray>=v2022.12.0
Requires-Dist: zarr>=2.14.2
Provides-Extra: docs
Requires-Dist: jupyter-sphinx; extra == 'docs'
Requires-Dist: nbsphinx; extra == 'docs'
Requires-Dist: nbsphinx-link; extra == 'docs'
Requires-Dist: pypandoc; extra == 'docs'
Requires-Dist: pytest-check-links; extra == 'docs'
Requires-Dist: recommonmark; extra == 'docs'
Requires-Dist: sphinx-rtd-theme; extra == 'docs'
Requires-Dist: sphinx>=1.5; extra == 'docs'
Provides-Extra: examples
Provides-Extra: test
Requires-Dist: nbval; extra == 'test'
Requires-Dist: pytest-cov; extra == 'test'
Requires-Dist: pytest>=6.0; extra == 'test'
